README.rst
setup.cfg
setup.py
./ctaplot/gammaboard/dashboard.ipynb
./share/gammaboard.gif
./share/CTA_Performance/CTA-Performance-prod3b-v1-20deg/CTA-Performance-prod3b-v1-North-20deg-05h-DiffSens.txt
./share/CTA_Performance/CTA-Performance-prod3b-v1-20deg/CTA-Performance-prod3b-v1-North-20deg-05h-EffArea.txt
./share/CTA_Performance/CTA-Performance-prod3b-v1-20deg/CTA-Performance-prod3b-v1-North-20deg-30m-DiffSens.txt
./share/CTA_Performance/CTA-Performance-prod3b-v1-20deg/CTA-Performance-prod3b-v1-North-20deg-30m-EffArea.txt
./share/CTA_Performance/CTA-Performance-prod3b-v1-20deg/CTA-Performance-prod3b-v1-North-20deg-50h-Angres.txt
./share/CTA_Performance/CTA-Performance-prod3b-v1-20deg/CTA-Performance-prod3b-v1-North-20deg-50h-BackgroundSqdeg.txt
./share/CTA_Performance/CTA-Performance-prod3b-v1-20deg/CTA-Performance-prod3b-v1-North-20deg-50h-DiffSens.txt
./share/CTA_Performance/CTA-Performance-prod3b-v1-20deg/CTA-Performance-prod3b-v1-North-20deg-50h-EffArea.txt
./share/CTA_Performance/CTA-Performance-prod3b-v1-20deg/CTA-Performance-prod3b-v1-North-20deg-50h-EffAreaNoDirectionCut.txt
./share/CTA_Performance/CTA-Performance-prod3b-v1-20deg/CTA-Performance-prod3b-v1-North-20deg-50h-Eres.txt
./share/CTA_Performance/CTA-Performance-prod3b-v1-20deg/CTA-Performance-prod3b-v1-South-20deg-05h-DiffSens.txt
./share/CTA_Performance/CTA-Performance-prod3b-v1-20deg/CTA-Performance-prod3b-v1-South-20deg-05h-EffArea.txt
./share/CTA_Performance/CTA-Performance-prod3b-v1-20deg/CTA-Performance-prod3b-v1-South-20deg-30m-DiffSens.txt
./share/CTA_Performance/CTA-Performance-prod3b-v1-20deg/CTA-Performance-prod3b-v1-South-20deg-30m-EffArea.txt
./share/CTA_Performance/CTA-Performance-prod3b-v1-20deg/CTA-Performance-prod3b-v1-South-20deg-50h-Angres.txt
./share/CTA_Performance/CTA-Performance-prod3b-v1-20deg/CTA-Performance-prod3b-v1-South-20deg-50h-BackgroundSqdeg.txt
./share/CTA_Performance/CTA-Performance-prod3b-v1-20deg/CTA-Performance-prod3b-v1-South-20deg-50h-DiffSens.txt
ctaplot.egg-info/PKG-INFO
ctaplot.egg-info/SOURCES.txt
ctaplot.egg-info/dependency_links.txt
ctaplot.egg-info/entry_points.txt
ctaplot.egg-info/requires.txt
ctaplot.egg-info/top_level.txt
