Metadata-Version: 2.1
Name: ctaplot
Version: 0.6.5
Summary: Compute and plot CTA IRFs
Home-page: https://github.com/cta-observatory/ctaplot
Author: Thomas Vuillaume, Mikael Jacquemont
Author-email: thomas.vuillaume@lapp.in2p3.fr
License: MIT
Classifier: Intended Audience :: Science/Research
Classifier: Programming Language :: Python :: 3
Classifier: Programming Language :: Python :: 3.9
Classifier: Programming Language :: Python :: 3.10
Classifier: Programming Language :: Python :: 3.11
Classifier: Topic :: Scientific/Engineering :: Astronomy
Requires-Python: >=3.9
